Metadata-Version: 2.1
Name: restmagic
Version: 0.7.1
Summary: HTTP REST magic for IPython
Home-page: https://github.com/b3b/ipython-restmagic
Author: b3b
Author-email: ash.b3b@gmail.com
License: MIT
Project-URL: Changelog, https://github.com/b3b/ipython-restmagic/blob/master/CHANGELOG.rst
Project-URL: Examples, https://nbviewer.jupyter.org/github/b3b/ipython-restmagic/tree/master/examples/
Keywords: magic rest http ipython jupyter
Platform: UNKNOWN
Classifier: Development Status :: 3 - Alpha
Classifier: Environment :: Console
Classifier: License :: OSI Approved :: MIT License
Classifier: Framework :: IPython
Classifier: Framework :: Jupyter
Classifier: Topic :: Internet :: WWW/HTTP
Classifier: Programming Language :: Python :: 3.6
Classifier: Programming Language :: Python :: 3.7
Classifier: Programming Language :: Python :: 3.8
Classifier: Programming Language :: Python :: 3.9
